queueCrypt/__init__.py
queueCrypt/errors.py
queueCrypt/queue.py
queueCrypt/ext/Encryption.py
queueCrypt/ext/__init__.py
queueCrypt-0.0.2.dist-info/Licence.txt
queueCrypt-0.0.2.dist-info/METADATA
queueCrypt-0.0.2.dist-info/WHEEL
queueCrypt-0.0.2.dist-info/top_level.txt
queueCrypt-0.0.2.dist-info/RECORD
