Metadata-Version: 2.1
Name: queueCrypt
Version: 0.0.2
Summary: A library that creates a queue and secures it better.
Home-page: UNKNOWN
Author: Daniel Katz
Author-email: 
License: MIT
Platform: UNKNOWN
Classifier: License :: OSI Approved :: MIT License
Classifier: Programming Language :: Python :: 3
Classifier: Operating System :: Microsoft :: Windows
Requires-Dist: queueCrypt
